ucamcl/__init__.py
ucamcl/autograder.py
ucamcl-1.0.11.dist-info/LICENSE
ucamcl-1.0.11.dist-info/METADATA
ucamcl-1.0.11.dist-info/WHEEL
ucamcl-1.0.11.dist-info/top_level.txt
ucamcl-1.0.11.dist-info/RECORD
