Metadata-Version: 2.1
Name: ucamcl
Version: 1.0.11
Summary: Teaching with Python unit tests
Home-page: https://github.com/damonjw/ucamcl
Author: Damon Wischik
Author-email: djw1005@cam.ac.uk
License: AGPLv3+
Keywords: education teaching testing
Platform: UNKNOWN
Classifier: Development Status :: 3 - Alpha
Classifier: Intended Audience :: Education
Classifier: Topic :: Education :: Computer Aided Instruction (CAI)
Classifier: License :: OSI Approved :: GNU Affero General Public License v3 or later (AGPLv3+)
Classifier: Programming Language :: Python :: 3
Classifier: Programming Language :: Python :: 3.6
Requires-Dist: cryptography (>=2.0)
Requires-Dist: requests
